OpenApiDriver/__init__.py
OpenApiDriver/openapi_executors.py
OpenApiDriver/openapi_reader.py
OpenApiDriver/openapidriver.libspec
OpenApiDriver/openapidriver.py
OpenApiDriver/py.typed
robotframework_openapidriver-4.3.0.dist-info/LICENSE
robotframework_openapidriver-4.3.0.dist-info/METADATA
robotframework_openapidriver-4.3.0.dist-info/WHEEL
robotframework_openapidriver-4.3.0.dist-info/RECORD
