Metadata-Version: 2.1
Name: robotframework-openapidriver
Version: 4.3.0
Summary: A library for contract-testing OpenAPI / Swagger APIs.
Home-page: https://github.com/MarketSquare/robotframework-openapidriver
License: Apache-2.0
Author: Robin Mackaij
Author-email: r.a.mackaij@gmail.com
Maintainer: Robin Mackaij
Maintainer-email: r.a.mackaij@gmail.com
Requires-Python: >=3.8,<4.0
Classifier: Framework :: Robot Framework
Classifier: License :: OSI Approved :: Apache Software License
Classifier: Operating System :: OS Independent
Classifier: Programming Language :: Python :: 3
Classifier: Programming Language :: Python :: 3.8
Classifier: Programming Language :: Python :: 3.9
Classifier: Programming Language :: Python :: 3.10
Classifier: Programming Language :: Python :: 3.11
Classifier: Programming Language :: Python :: 3.12
Classifier: Topic :: Software Development :: Testing
Classifier: Topic :: Software Development :: Testing :: Acceptance
Requires-Dist: robotframework-datadriver (>=1.6.1)
Requires-Dist: robotframework-openapi-libcore (>=1.11.0,<2.0.0)
